Metadata-Version: 2.4
Name: copr-backend
Version: 2.11
Summary: Python client for copr service.
Home-page: https://github.com/fedora-copr/copr
Author: Copr Team
Author-email: copr-team@redhat.com
License: GPLv2+
License-File: LICENSE
Dynamic: author
Dynamic: author-email
Dynamic: description
Dynamic: home-page
Dynamic: license
Dynamic: license-file
Dynamic: summary
